qsreplace.py
qsreplace-0.0.4.post1.dist-info/LICENSE
qsreplace-0.0.4.post1.dist-info/METADATA
qsreplace-0.0.4.post1.dist-info/WHEEL
qsreplace-0.0.4.post1.dist-info/top_level.txt
qsreplace-0.0.4.post1.dist-info/RECORD
