Metadata-Version: 2.1
Name: qsreplace
Version: 0.0.4.post1
Summary: A utility to replace query parameters in URLs
Home-page: https://github.com/basedygt/qsreplace
Author: basedygt
Author-email: basedygt@gmail.com
License: Apache-2.0 License
Keywords: qsreplace,url editor,params editor
License-File: LICENSE
Requires-Dist: urllib3
